aws_iam_tester/__init__.py
aws_iam_tester/__main__.py
aws_iam_tester/cli.py
aws_iam_tester/lib/__init__.py
aws_iam_tester/lib/aws_iam_tester.py
aws_iam_tester-1.0.6.dist-info/LICENSE
aws_iam_tester-1.0.6.dist-info/METADATA
aws_iam_tester-1.0.6.dist-info/WHEEL
aws_iam_tester-1.0.6.dist-info/entry_points.txt
aws_iam_tester-1.0.6.dist-info/RECORD
