Metadata-Version: 2.1
Name: aws-iam-tester
Version: 1.0.6
Summary: AWS IAM tester - simple command-line tool to check permissions handed out to IAM users and roles.
Home-page: https://github.com/gercograndia/aws-iam-tester
License: MIT
Keywords: AWS,IAM,Policy,Tester,Evaluation,Simulator
Author: Gerco Grandia
Author-email: gerco.grandia@4synergy.nl
Requires-Python: >=3.7.2,<4.0.0
Classifier: License :: OSI Approved :: MIT License
Classifier: Programming Language :: Python :: 3
Classifier: Programming Language :: Python :: 3.8
Classifier: Programming Language :: Python :: 3.9
Classifier: Programming Language :: Python :: 3.10
Classifier: Programming Language :: Python :: 3.11
Classifier: Programming Language :: Python :: 3.12
Requires-Dist: boto3 (>=1.26.26,<2.0.0)
Requires-Dist: click (>=8.1.3,<9.0.0)
Requires-Dist: outdated (>=0.2.2,<0.3.0)
Requires-Dist: pyyaml (>=6.0,<7.0)
Requires-Dist: six (>=1.16.0,<2.0.0)
Requires-Dist: tabulate (>=0.9.0,<0.10.0)
Requires-Dist: termcolor (>=2.1.0,<3.0.0)
Project-URL: Documentation, https://github.com/gercograndia/aws-iam-tester/blob/master/README.md
Project-URL: Repository, https://github.com/gercograndia/aws-iam-tester
Project-URL: issues, https://github.com/gercograndia/aws-iam-tester/issues
